amsync/__init__.py
amsync/bot.py
amsync/dataclass.py
amsync/db.py
amsync/enum.py
amsync/exceptions.py
amsync/image.py
amsync/obj.py
amsync/utils.py
amsync/ws.py
scripts/__init__.py
scripts/amsync.py
Amsync-0.0.53.dist-info/LICENSE
Amsync-0.0.53.dist-info/METADATA
Amsync-0.0.53.dist-info/WHEEL
Amsync-0.0.53.dist-info/entry_points.txt
Amsync-0.0.53.dist-info/top_level.txt
Amsync-0.0.53.dist-info/RECORD
