Metadata-Version: 2.1
Name: Amsync
Version: 0.0.53
Summary: An async library to easily create bots for the amino.
Home-page: https://github.com/ellandor/Amsync
Author: SempreLegit
License: MIT
Keywords: aminoapps,amino-py,amino,amino-bot,narvii,api,python,python3,python3.x,amino-async
Platform: UNKNOWN
Classifier: License :: OSI Approved :: MIT License
Classifier: Operating System :: Microsoft :: Windows
Classifier: Programming Language :: Python :: 3.8
Classifier: Programming Language :: Python :: 3.9
License-File: LICENSE
Requires-Dist: aiohttp
Requires-Dist: ujson
Requires-Dist: pybase64
Requires-Dist: peewee
Requires-Dist: python-dotenv
Requires-Dist: pillow
Requires-Dist: colorama
Requires-Dist: filetype
